macusers/__init__.py
macusers-0.0.3.dist-info/LICENSE
macusers-0.0.3.dist-info/METADATA
macusers-0.0.3.dist-info/WHEEL
macusers-0.0.3.dist-info/top_level.txt
macusers-0.0.3.dist-info/RECORD
