Metadata-Version: 2.1
Name: macusers
Version: 0.0.3
Summary: Get the macOS console username and/or a list of local non-system users.
Home-page: https://github.com/bryanheinz/python-macusers
Author: Bryan Heinz
Author-email: pypi@bryanheinz.com
License: UNKNOWN
Platform: UNKNOWN
Classifier: Programming Language :: Python :: 3
Classifier: License :: OSI Approved :: MIT License
Classifier: Operating System :: MacOS
